smolarith-0.2.0.dist-info/METADATA
smolarith-0.2.0.dist-info/WHEEL
smolarith-0.2.0.dist-info/licenses/LICENSE.md
smolarith/__init__.py
smolarith/div.py
smolarith/mul.py
smolarith/version.txt
smolarith-0.2.0.dist-info/RECORD
