Metadata-Version: 2.1
Name: smolarith
Version: 0.2.0
Summary: Soft-core arithmetic components written in Amaranth HDL
Keywords: multiplication,division,HDL,cpu
Author-Email: "William D. Jones" <thor0505@comcast.net>
License: BSD 2-Clause License
Classifier: Development Status :: 3 - Alpha
Classifier: Intended Audience :: Developers
Classifier: Intended Audience :: Telecommunications Industry
Classifier: Intended Audience :: Science/Research
Classifier: Intended Audience :: Other Audience
Classifier: License :: OSI Approved :: BSD License
Classifier: Operating System :: OS Independent
Classifier: Programming Language :: Python :: 3.8
Project-URL: Documentation, https://smolarith.readthedocs.io
Project-URL: Repository, https://github.com/cr1901/smolarith
Requires-Python: >=3.8
Requires-Dist: amaranth>=0.5.0
